README.md
setup.py
twikenizer/Twikenizer.py
twikenizer/__init__.py
twikenizer.egg-info/PKG-INFO
twikenizer.egg-info/SOURCES.txt
twikenizer.egg-info/dependency_links.txt
twikenizer.egg-info/not-zip-safe
twikenizer.egg-info/top_level.txt