Metadata-Version: 2.1
Name: twikenizer
Version: 1.0
Summary: Tokenizer for Twitter comments (tweets)
Home-page: https://github.com/Guilherme-Routar/Twikenizer
Author: Guilherme Routar
Author-email: groutar@gmail.com
License: MIT
Platform: UNKNOWN
Classifier: Programming Language :: Python :: 3
Classifier: License :: OSI Approved :: MIT License
Classifier: Operating System :: OS Independent
